nfon_api_client/__init__.py
nfon_api_client/base.py
nfon_api_client/endpoints.py
nfon_api_client/exceptions.py
nfon_api_client-0.1.0.dist-info/licenses/LICENSE
nfon_api_client-0.1.0.dist-info/METADATA
nfon_api_client-0.1.0.dist-info/WHEEL
nfon_api_client-0.1.0.dist-info/top_level.txt
nfon_api_client-0.1.0.dist-info/RECORD
