Metadata-Version: 2.4
Name: nfon-api-client
Version: 0.1.0
Summary: Authenticated API client for the NFON Service Portal 3
Home-page: https://github.com/Eddiedigits/nfon-api-client
Author: Paul Ellis
Author-email: paul.ellis@ac-telebusiness.net
License: MIT
Classifier: Development Status :: 4 - Beta
Classifier: Intended Audience :: Developers
Classifier: Topic :: Internet :: WWW/HTTP
Classifier: License :: OSI Approved :: MIT License
Classifier: Programming Language :: Python :: 3.8
Classifier: Programming Language :: Python :: 3.9
Classifier: Programming Language :: Python :: 3.10
Requires-Python: >=3.8
License-File: LICENSE
Requires-Dist: requests>=2.25.0
Requires-Dist: tenacity>=8.0.0
Dynamic: license-file
